{
  "Ads": [
      {
     "select_main_ads": "ADMOB",
      "select_backup_ads":"ALIEN-V",
      "main_ads_banner": "ca-app-pub-9676953921795368/2399473687",
      "main_ads_intertitial":"ca-app-pub-9676953921795368/1449246958",
      "main_ads_natives":"ca-app-pub-9676953921795368/7823083616",
      "main_ads_rewards":"ca-app-pub-9676953921795368/9966285747",
      "backup_ads_natives":"",
      "backup_ads_banner":"",
      "backup_ads_intertitial":"",
      "backup_ads_rewards":"",
      "open_ads_admob":"ca-app-pub-9676953921795368/9492283656",
      "open_ads_alien":"",
      "switch_open_ads":"1",
      "switch_banner_natives_ads":"",
      "interval_intertitial": 6,
      "initialize_sdk":"",
      "initialize_sdk_backup_ads":"",
      "high_paying_keyword_1": "",
      "high_paying_keyword_2": "",
      "high_paying_keyword_3": "",
      "high_paying_keyword_4": "",
      "high_paying_keyword_5": "",
      "status_app": "0",
      "link_redirect": "https://"
      }
   ],

  "More":
  [
    {
      "id":1,
      "title":"ARYA SAlAKO",
      "image":"file:///android_asset/aldebaran.png",
      "link":"https://play.google.com/store/apps/details?id=prank.wavideocall.arya.saloka.aldebaran.offline"
    },
	{
      "id":2,
      "title":"Naisa Alifia",
      "image":"file:///android_asset/naisaalifia.png",
      "link":"https://play.google.com/store/apps/details?id=fake.video.call.dengan.naisa.alifia.yuriza.nay.terbaru.offline"
    },
	{
      "id":3,
      "title":"AMANDA MANOPO",
      "image":"file:///android_asset/manopo.png",
      "link":"https://play.google.com/store/apps/details?id=prank.video.call.amanda.manopo.full.offline"
    },
    {
      "id":4,
      "title":"RIA RICIS",
      "image":"file:///android_asset/riaricis.png",
      "link":"https://play.google.com/store/apps/details?id=fake.video.call.dengan.ria.ricis.full.offline.terbaru"
    },
    {
      "id":5,
      "title":"SULE",
      "image":"file:///android_asset/sule.png",
      "link":"https://play.google.com/store/apps/details?id=fake.video.call.dengan.ferdinan.sule.terbaru.offline"
    },
    {
      "id":6,
      "title":"AYU TING TING",
      "image":"file:///android_asset/ayu.png",
      "link":"https://play.google.com/store/apps/details?id=fake.call.wavideo.dengan.ayu.ting.ting.terbaru.offline"
    }
  ],
  "Item":
  [
    {
      "id":1,
      "name":"Habib Alwi Assegaf 1",
      "image_url":"file:///android_asset/baibaliwiphoto1.webp",
      "video_url":"habibalwivideo1",
      "voice_url":"habibalwisuarajoss1.mp3"
    },
    {
      "id":2,
      "name":"Habib Alwi Assegaf 2",
      "image_url":"file:///android_asset/baibaliwiphoto2.webp",
      "video_url":"habibalwivideo2",
      "voice_url":"habibalwisuarajoss2.mp3"
    },
    {
      "id":3,
      "name":"Habib Alwi Assegaf 3",
      "image_url":"file:///android_asset/baibaliwiphoto3.webp",
      "video_url":"habibalwivideo3",
      "voice_url":"habibalwisuarajoss3.mp3"
    },
    {
      "id":4,
      "name":"Habib Alwi Assegaf 4",
      "image_url":"file:///android_asset/baibaliwiphoto4.webp",
      "video_url":"habibalwivideo1",
      "voice_url":"habibalwisuarajoss1.mp3"
    },
	{
      "id":5,
      "name":"AHabib Alwi Assegaf 5",
      "image_url":"file:///android_asset/baibaliwiphoto5.webp",
      "video_url":"habibalwivideo2",
      "voice_url":"habibalwisuarajoss2.mp3"
    },
    {
      "id":6,
      "name":"Habib Alwi Assegaf 6",
      "image_url":"file:///android_asset/baibaliwiphoto6.webp",
      "video_url":"habibalwivideo3",
      "voice_url":"habibalwisuarajoss3.mp3"
    },
    {
      "id":7,
      "name":"Habib Alwi Assegaf 7",
      "image_url":"file:///android_asset/baibaliwiphoto7.webp",
      "video_url":"habibalwivideo1",
      "voice_url":"habibalwisuarajoss1.mp3"
    },
    {
      "id":8,
      "name":"Habib Alwi Assegaf 8",
      "image_url":"file:///android_asset/baibaliwiphoto8.webp",
      "video_url":"habibalwivideo2",
      "voice_url":"habibalwisuarajoss2.mp3"
    },
    {
      "id":9,
      "name":"Habib Alwi Assegaf 9",
      "image_url":"file:///android_asset/baibaliwiphoto9.webp",
      "video_url":"habibalwivideo3",
      "voice_url":"habibalwisuarajoss3.mp3"
    }
  ]

}
